cligpt/__init__.py
cligpt/__main__.py
cligpt/cli.py
cligpt/cligpt.py
cligpt/config.json
cligpt-2.8.dist-info/LICENSE
cligpt-2.8.dist-info/METADATA
cligpt-2.8.dist-info/WHEEL
cligpt-2.8.dist-info/entry_points.txt
cligpt-2.8.dist-info/top_level.txt
cligpt-2.8.dist-info/RECORD
