Metadata-Version: 2.1
Name: cligpt
Version: 2.8
Summary: A handy CLI interface for ChatGPT
Home-page: http://www.example.com/~cschultz/bvote/
Author: skvn
Author-email: xxx@gmail.com
Project-URL: Bug Tracker, http://bitbucket.org/tarek/distribute/issues/
Classifier: Programming Language :: Python :: 3
Classifier: License :: OSI Approved :: MIT License
Classifier: Operating System :: OS Independent
Requires-Python: >=3.6
License-File: LICENSE
Requires-Dist: openai
Requires-Dist: rich
Requires-Dist: pyperclip
